omero/plugins/metadata.py
omero_metadata/__init__.py
omero_metadata/cli.py
omero_metadata/populate.py
omero_metadata-0.13.0.dist-info/LICENSE.txt
omero_metadata-0.13.0.dist-info/METADATA
omero_metadata-0.13.0.dist-info/WHEEL
omero_metadata-0.13.0.dist-info/top_level.txt
omero_metadata-0.13.0.dist-info/zip-safe
omero_metadata-0.13.0.dist-info/RECORD
