Metadata-Version: 2.1
Name: omero-metadata
Version: 0.13.0
Summary: Metadata plugin for use in the OMERO CLI.
Home-page: https://github.com/ome/omero-metadata/
Author: The Open Microscopy Team
Author-email: ome-devel@lists.openmicroscopy.org.uk
License: GPL-2.0+
Download-URL: https://github.com/ome/omero-metadata//v0.13.0.tar.gz
Keywords: OMERO.CLI,plugin
Platform: UNKNOWN
Classifier: Development Status :: 4 - Beta
Classifier: Environment :: Plugins
Classifier: Intended Audience :: Developers
Classifier: Intended Audience :: End Users/Desktop
Classifier: License :: OSI Approved :: GNU General Public License v2 or later (GPLv2+)
Classifier: Natural Language :: English
Classifier: Operating System :: OS Independent
Classifier: Programming Language :: Python :: 3
Classifier: Topic :: Software Development :: Libraries :: Python Modules
Requires-Python: >=3
License-File: LICENSE.txt
Requires-Dist: PyYAML
Requires-Dist: jinja2
Requires-Dist: omero-py (>=5.6.0)
Requires-Dist: pandas
